{
  "id": "suspense-reversal",
  "name": "悬疑反转短剧",
  "category": "suspense",
  "description": "经典三幕悬疑结构，从平静表象到危机升级再到真相反转。适合30-90秒短视频。",
  "targetDuration": 60,
  "targetPlatform": "portrait",
  "structure": {
    "acts": [
      {
        "title": "第一幕：表面平静",
        "description": "建立日常场景，植入微妙异常元素",
        "scenes": [
          {
            "title": "日常场景",
            "description": "主角的日常生活，看似一切正常",
            "suggestedShotTypes": ["wide", "medium"],
            "metadata": { "duration": 15, "timeOfDay": "day", "location": "家中" }
          },
          {
            "title": "第一个异常",
            "description": "一个微小的不一致引起主角注意",
            "suggestedShotTypes": ["close-up", "insert"],
            "metadata": { "duration": 15, "timeOfDay": "day", "location": "家中" }
          }
        ]
      },
      {
        "title": "第二幕：危机升级",
        "description": "主角主动调查，发现更多疑点，对手现身",
        "scenes": [
          {
            "title": "搜寻线索",
            "description": "主角开始主动寻找答案",
            "suggestedShotTypes": ["medium", "close-up", "pov"],
            "suggestedCameraMovement": "handheld",
            "metadata": { "duration": 15, "timeOfDay": "evening", "location": "室外" }
          },
          {
            "title": "对手现身",
            "description": "危机达到顶点，主角陷入困境",
            "suggestedShotTypes": ["wide", "close-up"],
            "suggestedCameraMovement": "dolly",
            "metadata": { "duration": 15, "timeOfDay": "night", "location": "室外" }
          }
        ]
      },
      {
        "title": "第三幕：反转真相",
        "description": "出乎意料的真相揭露，结局留下余味",
        "scenes": [
          {
            "title": "真相揭露",
            "description": "颠覆之前所有认知的真相浮现",
            "suggestedShotTypes": ["close-up", "wide"],
            "suggestedCameraMovement": "static",
            "metadata": { "duration": 15, "timeOfDay": "night", "location": "室内" }
          },
          {
            "title": "尾声镜头",
            "description": "一个安静的画面让观众久久回味",
            "suggestedShotTypes": ["wide"],
            "suggestedCameraMovement": "static",
            "metadata": { "duration": 5, "timeOfDay": "night", "location": "室内" }
          }
        ]
      }
    ]
  },
  "stylePresets": {
    "colorPalette": ["#1a1a2e", "#16213e", "#0f3460", "#e94560"],
    "pacing": "fast",
    "visualStyle": "冷蓝灰调 · 高对比 · 电影感"
  },
  "tags": ["悬疑", "反转", "短剧", "30-90秒"],
  "author": "Spellpaw",
  "downloads": 0,
  "version": 1
}
